{
  "name": "signal-send",
  "description": "Send a Signal message to a person (by their E.164 phone number) or a group (by group ID). For 1:1 sends, use the contact's verified Signal phone number from contact-lookup — display names are not trusted for Signal identity. For group sends, all group members must be verified contacts; unverified groups are refused with a list of which members need verification.",
  "version": "1.0.0",
  "sensitivity": "normal",
  "action_risk": "medium",
  "inputs": {
    "recipient": "string?",
    "group_id": "string?",
    "message": "string"
  },
  "outputs": {
    "delivered_to": "string",
    "channel": "string"
  },
  "permissions": [],
  "secrets": [],
  "timeout": 30000,
  "capabilities": [
    "outboundGateway"
  ]
}
