{
  "name": "calendar-update-event",
  "description": "Modify an existing calendar event. Supports partial updates — only provide the fields that need changing (title, time, description, location, attendees, conferencing). Attendee changes trigger invitation updates.",
  "version": "1.0.0",
  "sensitivity": "normal",
  "action_risk": "high",
  "infrastructure": true,
  "inputs": {
    "calendarId": "string",
    "eventId": "string",
    "title": "string?",
    "start": "timestamp? (new event start time)",
    "end": "timestamp? (new event end time)",
    "description": "string?",
    "location": "string?",
    "attendees": "object[]? (list of attendees to set, each with email and optional name)",
    "conferencing": "object?",
    "colorId": "string?",
    "reminders": "object?"
  },
  "outputs": {
    "event": "object"
  },
  "permissions": [],
  "secrets": [],
  "timeout": 30000
}
